{
    "AX": {
        "error": 0.052132079369142215, 
        "fit": "average_SEM", 
        "value": -0.01219546981677316
    }, 
    "CDD": {
        "error": 0.00019221663473918262, 
        "fit": "average_SEM", 
        "value": 0.00028190762365435756
    }, 
    "H1": {
        "error": 0.11776368071624167, 
        "fit": "average_SEM", 
        "value": 0.0542163224752585
    }, 
    "H2": {
        "error": 0.12347172527729064, 
        "fit": "average_SEM", 
        "value": -0.018749581949668935
    }, 
    "L1": {
        "error": 0.11222632111161093, 
        "fit": "average_SEM", 
        "value": -0.08238677370815518
    }, 
    "L2": {
        "error": 0.14057739742773742, 
        "fit": "average_SEM", 
        "value": -0.008811010102120539
    }
}