{
    "AX": {
        "error": 0.05375946034437011, 
        "fit": "average_SEM", 
        "value": -0.002696732456388418
    }, 
    "CDD": {
        "error": 0.0001909579462551965, 
        "fit": "average_SEM", 
        "value": 0.0002495659185418238
    }, 
    "H1": {
        "error": 0.1098917555180855, 
        "fit": "average_SEM", 
        "value": 0.06498150271751607
    }, 
    "H2": {
        "error": 0.12699082577837126, 
        "fit": "average_SEM", 
        "value": 0.03575604445650242
    }, 
    "L1": {
        "error": 0.0999283740753734, 
        "fit": "average_SEM", 
        "value": -0.01505832556867972
    }, 
    "L2": {
        "error": 0.2575834988196757, 
        "fit": "average_SEM", 
        "value": 0.3855560461563679
    }
}