{
    "AX": {
        "error": 0.054150464415551276, 
        "fit": "average", 
        "value": -0.08276950140767124
    }, 
    "CDD": {
        "error": 0.00016970709484407366, 
        "fit": "average", 
        "value": 0.00021391364328640823
    }, 
    "H1": {
        "error": 0.08821965965491879, 
        "fit": "average", 
        "value": 0.010378585602925991
    }, 
    "H2": {
        "error": 0.09047473078523302, 
        "fit": "average", 
        "value": -0.025444040522541338
    }, 
    "L1": {
        "error": 0.09178038434367813, 
        "fit": "average", 
        "value": -0.07169341138539324
    }, 
    "L2": {
        "error": 0.10425725590316944, 
        "fit": "average", 
        "value": -0.013758093099093345
    }
}