{
    "AX": {
        "error": 0.052797995013631555, 
        "fit": "average_SEM", 
        "value": -0.015444705709038923
    }, 
    "CDD": {
        "error": 3.1664556985604686e-05, 
        "fit": "average_SEM", 
        "value": -5.4327303385232676e-06
    }, 
    "H1": {
        "error": 0.11363787973451007, 
        "fit": "average_SEM", 
        "value": 0.0030622116678083937
    }, 
    "H2": {
        "error": 0.11969094477402273, 
        "fit": "average_SEM", 
        "value": -0.022039351378852087
    }, 
    "L1": {
        "error": 0.10909940061714538, 
        "fit": "average_SEM", 
        "value": -0.07459780654559532
    }, 
    "L2": {
        "error": 0.13729981411690495, 
        "fit": "average_SEM", 
        "value": -0.02897409310745489
    }
}