{
    "Ar36": {
        "error": 0.017747205708981664, 
        "fit": "parabolic", 
        "value": 2.0653861050770104
    }, 
    "Ar37": {
        "error": 0.34331959602248224, 
        "fit": "linear", 
        "value": 168.01377769656381
    }, 
    "Ar38": {
        "error": 0.11833362099246261, 
        "fit": "linear", 
        "value": 2.2413035595439981
    }, 
    "Ar39": {
        "error": 0.082133111145550414, 
        "fit": "parabolic", 
        "value": 41.407596360096278
    }, 
    "Ar40": {
        "error": 0.29308546338801444, 
        "fit": "parabolic", 
        "value": 618.11731576264037
    }, 
    "Ar41": {
        "error": 0.11239514870708524, 
        "fit": "average_SEM", 
        "value": 0.1946705047506839
    }
}