{
    "AX": {
        "error": 0.04886790571413908, 
        "fit": "average", 
        "value": -0.076615331722584
    }, 
    "CDD": {
        "error": 9.090900911298224e-05, 
        "fit": "average", 
        "value": 5.7298297178931534e-05
    }, 
    "H1": {
        "error": 0.10031131905632595, 
        "fit": "average", 
        "value": 0.038528603218608244
    }, 
    "H2": {
        "error": 0.09572897415652212, 
        "fit": "average", 
        "value": -0.04087562833231894
    }, 
    "L1": {
        "error": 0.10934435760482451, 
        "fit": "average", 
        "value": -0.058123327644653215
    }, 
    "L2": {
        "error": 0.1253927588651399, 
        "fit": "average", 
        "value": -0.020219721205147177
    }
}