{
    "AX": {
        "error": 0.05238488532336481, 
        "fit": "average_SEM", 
        "value": -0.017588010772791072
    }, 
    "CDD": {
        "error": 0.00014502215898538993, 
        "fit": "average_SEM", 
        "value": 0.00012223636780011777
    }, 
    "H1": {
        "error": 0.10835386102128622, 
        "fit": "average_SEM", 
        "value": 0.22187468071933836
    }, 
    "H2": {
        "error": 0.11485275345786852, 
        "fit": "average_SEM", 
        "value": 0.11983546858051947
    }, 
    "L1": {
        "error": 0.10350214541330727, 
        "fit": "average_SEM", 
        "value": 0.08814717795600396
    }, 
    "L2": {
        "error": 0.18162430001637078, 
        "fit": "average_SEM", 
        "value": 0.36413016406974447
    }
}