{
    "Ar36": {
        "error": 0.0088303284248425571, 
        "fit": "Parabolic", 
        "value": 0.70778049494768391
    }, 
    "Ar37": {
        "error": 0.11527966446808521, 
        "fit": "linear", 
        "value": 4.5440787447890187
    }, 
    "Ar38": {
        "error": 0.096886695184806554, 
        "fit": "linear", 
        "value": 0.36324898821872059
    }, 
    "Ar39": {
        "error": 0.055748142820680822, 
        "fit": "Parabolic", 
        "value": 5.9932081301413644
    }, 
    "Ar40": {
        "error": 0.18728618738942818, 
        "fit": "Parabolic", 
        "value": 229.19590476781246
    }, 
    "Ar41": {
        "error": 0.10583868258514899, 
        "fit": "linear", 
        "value": -0.0039840523984780198
    }
}