{
    "Ar36": {
        "error": 0.010121887550138478, 
        "fit": "Parabolic", 
        "value": 0.86658824778282839
    }, 
    "Ar37": {
        "error": 0.12219637043180208, 
        "fit": "linear", 
        "value": 5.2680490443673644
    }, 
    "Ar38": {
        "error": 0.099936848036247819, 
        "fit": "linear", 
        "value": 0.45274579123309638
    }, 
    "Ar39": {
        "error": 0.051910900970204996, 
        "fit": "Parabolic", 
        "value": 7.913610023654833
    }, 
    "Ar40": {
        "error": 0.1982742735731412, 
        "fit": "Parabolic", 
        "value": 267.43776746620443
    }, 
    "Ar41": {
        "error": 0.10172728956418876, 
        "fit": "linear", 
        "value": 0.0044880439371336881
    }
}